adaptavist/__init__.py
adaptavist/_helper.py
adaptavist/adaptavist.py
adaptavist/const.py
adaptavist/py.typed
adaptavist-2.4.0.dist-info/LICENSE.md
adaptavist-2.4.0.dist-info/METADATA
adaptavist-2.4.0.dist-info/WHEEL
adaptavist-2.4.0.dist-info/top_level.txt
adaptavist-2.4.0.dist-info/RECORD
