Metadata-Version: 2.1
Name: adaptavist
Version: 2.4.0
Summary: python package providing functionality for Jira Test Management (tm4j)
Home-page: https://github.com/devolo/adaptavist
Author: Stephan Steinberg, Guido Schmitz, Markus Bong
Author-email: guido.schmitz@devolo.de, markus.bong@devolo.de
License: MIT
Keywords: python adaptavist kanoah tm4j jira test testmanagement report
Platform: any
Classifier: Intended Audience :: Developers
Classifier: License :: OSI Approved :: MIT License
Classifier: Operating System :: OS Independent
Classifier: Programming Language :: Python
Classifier: Programming Language :: Python :: 3
Classifier: Topic :: Software Development :: Quality Assurance
Classifier: Topic :: Software Development :: Testing
Classifier: Topic :: Utilities
Classifier: Topic :: Software Development :: Libraries :: Python Modules
Requires-Python: >=3.6
License-File: LICENSE.md
Requires-Dist: requests-toolbelt
Requires-Dist: requests
Requires-Dist: importlib-metadata ; python_version < "3.8"
Provides-Extra: docs
Requires-Dist: m2r2 ; extra == 'docs'
Requires-Dist: pydata-sphinx-theme ; extra == 'docs'
Requires-Dist: sphinx ; extra == 'docs'
Provides-Extra: test
Requires-Dist: pytest ; extra == 'test'
Requires-Dist: requests-mock ; extra == 'test'
